backports/__init__.py
backports/print_function.py
backports.print_function-1.1.1.dist-info/DESCRIPTION.rst
backports.print_function-1.1.1.dist-info/METADATA
backports.print_function-1.1.1.dist-info/RECORD
backports.print_function-1.1.1.dist-info/WHEEL
backports.print_function-1.1.1.dist-info/metadata.json
backports.print_function-1.1.1.dist-info/top_level.txt
